LAB2/fsm-assignments/problem3_vending/vending_mealy.v
`timescale 1ns/1ps
// Mealy vending machine: price = 20
// coin[1:0]: 01 -> 5, 10 -> 10, 00/11 -> idle/ignore
// dispense: 1-cycle pulse when total >= 20
// chg5:     1-cycle pulse when total == 25
module vending_mealy(
    input  wire       clk,
    input  wire       rst,        // synchronous, active-high
    input  wire [1:0] coin,       // 01=5, 10=10, 00/11=idle/ignore
    output reg        dispense,   // 1-cycle pulse
    output reg        chg5        // 1-cycle pulse with dispense on 25
);
    // State encodes running total: 0, 5, 10, 15
    localparam S0  = 2'd0;
    localparam S5  = 2'd1;
    localparam S10 = 2'd2;
    localparam S15 = 2'd3;

    reg [1:0] state, next;

    // Next-state + Mealy outputs
    always @* begin
        // defaults
        next     = state;
        dispense = 1'b0;
        chg5     = 1'b0;

        case (state)
            S0: begin
                case (coin)
                    2'b01: next = S5;    // +5
                    2'b10: next = S10;   // +10
                    default: next = S0;  // idle/ignore
                endcase
            end

            S5: begin
                case (coin)
                    2'b01: next = S10;   // 5+5
                    2'b10: next = S15;   // 5+10
                    default: next = S5;
                endcase
            end

            S10: begin
                case (coin)
                    2'b01: next = S15;   // 10+5
                    2'b10: begin         // 10+10 = 20 -> vend
                        dispense = 1'b1;
                        next     = S0;    // reset after vend
                    end
                    default: next = S10;
                endcase
            end

            S15: begin
                case (coin)
                    2'b01: begin         // 15+5 = 20 -> vend
                        dispense = 1'b1;
                        next     = S0;
                    end
                    2'b10: begin         // 15+10 = 25 -> vend + change
                        dispense = 1'b1;
                        chg5     = 1'b1;
                        next     = S0;
                    end
                    default: next = S15;
                endcase
            end
        endcase
    end

    // State register (sync, active-high reset)
    always @(posedge clk) begin
        if (rst) state <= S0;
        else     state <= next;
    end
endmodule

LAB2/fsm-assignments/problem3_vending/tb_vending_mealy.v
`timescale 1ns/1ps
module tb_vending_mealy;
    reg        clk = 1'b0;
    reg        rst = 1'b1;
    reg  [1:0] coin = 2'b00;   // 01->5, 10->10
    wire       dispense, chg5;

    // DUT
    vending_mealy dut(
        .clk(clk),
        .rst(rst),
        .coin(coin),
        .dispense(dispense),
        .chg5(chg5)
    );

    // 100 MHz clock
    always #5 clk = ~clk;

    // Drive exactly one coin for one cycle, then one idle cycle
    task put_coin(input [1:0] c);
        begin
            @(negedge clk); coin = c;
            @(negedge clk); coin = 2'b00; // idle between coins
        end
    endtask

    initial begin
        $dumpfile("vending_mealy.vcd");
        $dumpvars(0, tb_vending_mealy);

        // release reset
        repeat (2) @(negedge clk);
        rst = 1'b0;

        // Scenario 1: 10 + 10 => vend (no change)
        put_coin(2'b10);
        put_coin(2'b10);
        repeat (2) @(negedge clk);

        // Scenario 2: 5 + 5 + 5 + 5 => vend (no change)
        put_coin(2'b01);
        put_coin(2'b01);
        put_coin(2'b01);
        put_coin(2'b01);
        repeat (2) @(negedge clk);

        // Scenario 3: 5 + 10 + 10 => total 25 => vend + chg5
        put_coin(2'b01);
        put_coin(2'b10);
        put_coin(2'b10);
        repeat (3) @(negedge clk);

        // Ignore invalid/idle
        @(negedge clk); coin = 2'b11; // ignored
        @(negedge clk); coin = 2'b00;

        repeat (4) @(negedge clk);
        $finish;
    end
endmodule

LAB2/fsm-assignments/problem3_vending/waves/vending_mealy.vcd
$date
	Tue Aug 19 11:48:52 2025
$end
$version
	Icarus Verilog
$end
$timescale
	1ps
$end
$scope module tb_vending_mealy $end
$var wire 1 ! dispense $end
$var wire 1 " chg5 $end
$var reg 1 # clk $end
$var reg 2 $ coin [1:0] $end
$var reg 1 % rst $end
$scope module dut $end
$var wire 1 # clk $end
$var wire 2 & coin [1:0] $end
$var wire 1 % rst $end
$var reg 1 " chg5 $end
$var reg 1 ! dispense $end
$var reg 2 ' next [1:0] $end
$var reg 2 ( state [1:0] $end
$upscope $end
$scope task put_coin $end
$var reg 2 ) c [1:0] $end
$upscope $end
$upscope $end
$enddefinitions $end
#0
$dumpvars
bx )
bx (
bx '
b0 &
1%
b0 $
0#
0"
0!
$end
#5000
b0 '
b0 (
1#
#10000
0#
#15000
1#
#20000
b10 )
0%
0#
#25000
1#
#30000
b10 '
b10 $
b10 &
0#
#35000
b0 '
1!
b10 (
1#
#40000
0!
b10 '
b0 $
b0 &
0#
#45000
1#
#50000
b0 '
1!
b10 $
b10 &
0#
#55000
b10 '
0!
b0 (
1#
#60000
b0 '
b0 $
b0 &
0#
#65000
1#
#70000
0#
#75000
1#
#80000
b1 )
0#
#85000
1#
#90000
b1 '
b1 $
b1 &
0#
#95000
b10 '
b1 (
1#
#100000
b1 '
b0 $
b0 &
0#
#105000
1#
#110000
b10 '
b1 $
b1 &
0#
#115000
b11 '
b10 (
1#
#120000
b10 '
b0 $
b0 &
0#
#125000
1#
#130000
b11 '
b1 $
b1 &
0#
#135000
b0 '
1!
b11 (
1#
#140000
0!
b11 '
b0 $
b0 &
0#
#145000
1#
#150000
b0 '
1!
b1 $
b1 &
0#
#155000
b1 '
0!
b0 (
1#
#160000
b0 '
b0 $
b0 &
0#
#165000
1#
#170000
0#
#175000
1#
#180000
0#
#185000
1#
#190000
b1 '
b1 $
b1 &
0#
#195000
b10 '
b1 (
1#
#200000
b1 '
b10 )
b0 $
b0 &
0#
#205000
1#
#210000
b11 '
b10 $
b10 &
0#
#215000
b0 '
1"
1!
b11 (
1#
#220000
0"
0!
b11 '
b0 $
b0 &
0#
#225000
1#
#230000
b0 '
1"
1!
b10 $
b10 &
0#
#235000
b10 '
0"
0!
b0 (
1#
#240000
b0 '
b0 $
b0 &
0#
#245000
1#
#250000
0#
#255000
1#
#260000
0#
#265000
1#
#270000
0#
#275000
1#
#280000
b11 $
b11 &
0#
#285000
1#
#290000
b0 $
b0 &
0#
