LAB2/fsm-assignments/problem4_link/slave_fsm.v
// Slave: latch on req rising edge, assert ack for 2 cycles,
// then hold ack high until req goes low; expose last_byte for TB visibility.
module slave_fsm(
    input  wire       clk,
    input  wire       rst,       // synchronous active-high
    input  wire       req,       // from master
    input  wire [7:0] data_in,   // from master
    output reg        ack,       // to master
    output reg [7:0]  last_byte  // latched data (observable)
);
    reg req_d;           // for edge detection
    reg        ack_act;  // ack active flag
    reg [1:0]  hold;     // 2-cycle hold counter

    always @(posedge clk) begin
        if (rst) begin
            req_d     <= 1'b0;
            ack_act   <= 1'b0;
            hold      <= 2'd0;
            ack       <= 1'b0;
            last_byte <= 8'h00;
        end else begin
            req_d <= req;

            // On req rising edge, latch data and start 2-cycle ack hold
            if (req && !req_d) begin
                last_byte <= data_in;
                ack_act   <= 1'b1;
                hold      <= 2'd2;
            end

            // Decrement the 2-cycle hold while active
            if (ack_act && (hold != 2'd0)) begin
                hold <= hold - 2'd1;
            end

            // After hold is over, drop ack only after req is LOW
            if (ack_act && (hold == 2'd0) && !req) begin
                ack_act <= 1'b0;
            end

            ack <= ack_act;
        end
    end
endmodule

LAB2/fsm-assignments/problem4_link/master_fsm.v
// Master: drives 4 bytes with 4‑phase handshake
module master_fsm(
    input  wire       clk,
    input  wire       rst,   // synchronous active-high
    input  wire       ack,   // from slave
    output reg        req,   // to slave
    output reg [7:0]  data,  // to slave
    output reg        done   // 1-cycle pulse after 4 bytes
);

    // simple 4‑entry ROM (A0..A3) for the burst payload
    reg [7:0] rom [0:3];
    initial begin
        rom[0] = 8'hA0;
        rom[1] = 8'hA1;
        rom[2] = 8'hA2;
        rom[3] = 8'hA3;
    end

    localparam S_IDLE        = 3'd0,
               S_DRIVE       = 3'd1,
               S_WAIT_ACK_HI = 3'd2,
               S_DROP_REQ    = 3'd3,
               S_WAIT_ACK_LO = 3'd4,
               S_NEXT_BYTE   = 3'd5,
               S_DONE        = 3'd6;

    reg [2:0] state;
    reg [1:0] idx;  // 0..3

    always @(posedge clk) begin
        if (rst) begin
            state <= S_IDLE;
            idx   <= 2'd0;
            req   <= 1'b0;
            data  <= 8'h00;
            done  <= 1'b0;
        end else begin
            done <= 1'b0;  // default

            case (state)
                S_IDLE: begin
                    idx  <= 2'd0;
                    data <= rom[0];
                    req  <= 1'b0;
                    state <= S_DRIVE;
                end

                // Drive current byte and raise req
                S_DRIVE: begin
                    data <= rom[idx];
                    req  <= 1'b1;
                    state <= S_WAIT_ACK_HI;
                end

                // Wait for slave to assert ack
                S_WAIT_ACK_HI: begin
                    if (ack) state <= S_DROP_REQ;
                end

                // Drop req once ack is seen
                S_DROP_REQ: begin
                    req   <= 1'b0;
                    state <= S_WAIT_ACK_LO;
                end

                // Wait for slave to drop ack
                S_WAIT_ACK_LO: begin
                    if (!ack) begin
                        if (idx == 2'd3) state <= S_DONE;
                        else             state <= S_NEXT_BYTE;
                    end
                end

                // Advance to next byte
                S_NEXT_BYTE: begin
                    idx  <= idx + 2'd1;
                    data <= rom[idx + 2'd1];
                    state <= S_DRIVE;
                end

                // Pulse done for one cycle
                S_DONE: begin
                    done  <= 1'b1;
                    state <= S_IDLE;
                end

                default: state <= S_IDLE;
            endcase
        end
    end
endmodule

LAB2/fsm-assignments/problem4_link/link_top.v
// Top that wires master and slave together
module link_top(
    input  wire clk,
    input  wire rst,
    output wire done
);
    wire       req, ack;
    wire [7:0] data;
    wire [7:0] last_byte; // for waveform observation

    master_fsm u_master (
        .clk (clk),
        .rst (rst),
        .ack (ack),
        .req (req),
        .data(data),
        .done(done)
    );

    slave_fsm u_slave (
        .clk      (clk),
        .rst      (rst),
        .req      (req),
        .data_in  (data),
        .ack      (ack),
        .last_byte(last_byte)
    );
endmodule

LAB2/fsm-assignments/problem4_link/tb_link_top.v
`timescale 1ns/1ps
module tb_link_top;
    // clock & reset
    reg clk = 1'b0;
    reg rst = 1'b1;
    wire done;

    // DUT
    link_top dut(.clk(clk), .rst(rst), .done(done));

    // 100 MHz clock (10 ns period)
    always #5 clk = ~clk;

    initial begin
        // VCD
        $dumpfile("link.vcd");
        $dumpvars(0, tb_link_top);

        // Reset for a few cycles
        repeat (4) @(posedge clk);
        rst <= 1'b0;

        // Run until done is seen, then a few extra cycles
        wait (done === 1'b1);
        @(posedge clk);
        @(posedge clk);
        $finish;
    end
endmodule

LAB2/fsm-assignments/problem4_link/waves/link.vcd
$date
	Tue Aug 19 12:20:21 2025
$end
$version
	Icarus Verilog
$end
$timescale
	1ps
$end
$scope module tb_link_top $end
$var wire 1 ! done $end
$var reg 1 " clk $end
$var reg 1 # rst $end
$scope module dut $end
$var wire 1 " clk $end
$var wire 1 # rst $end
$var wire 1 $ req $end
$var wire 8 % last_byte [7:0] $end
$var wire 1 ! done $end
$var wire 8 & data [7:0] $end
$var wire 1 ' ack $end
$scope module u_master $end
$var wire 1 " clk $end
$var wire 1 # rst $end
$var wire 1 ' ack $end
$var reg 8 ( data [7:0] $end
$var reg 1 ! done $end
$var reg 2 ) idx [1:0] $end
$var reg 1 $ req $end
$var reg 3 * state [2:0] $end
$upscope $end
$scope module u_slave $end
$var wire 1 " clk $end
$var wire 8 + data_in [7:0] $end
$var wire 1 $ req $end
$var wire 1 # rst $end
$var reg 1 ' ack $end
$var reg 1 , ack_act $end
$var reg 2 - hold [1:0] $end
$var reg 8 . last_byte [7:0] $end
$var reg 1 / req_d $end
$upscope $end
$upscope $end
$upscope $end
$enddefinitions $end
#0
$dumpvars
x/
bx .
bx -
x,
bx +
bx *
bx )
bx (
x'
bx &
bx %
x$
1#
0"
x!
$end
#5000
0!
b0 &
b0 (
b0 +
0$
b0 )
b0 *
b0 %
b0 .
0'
b0 -
0,
0/
1"
#10000
0"
#15000
1"
#20000
0"
#25000
1"
#30000
0"
#35000
0#
1"
#40000
0"
#45000
b1 *
b10100000 &
b10100000 (
b10100000 +
1"
#50000
0"
#55000
b10 *
1$
1"
#60000
0"
#65000
b10 -
1,
b10100000 %
b10100000 .
1/
1"
#70000
0"
#75000
1'
b1 -
1"
#80000
0"
#85000
b11 *
b0 -
1"
#90000
0"
#95000
b100 *
0$
1"
#100000
0"
#105000
0,
0/
1"
#110000
0"
#115000
0'
1"
#120000
0"
#125000
b101 *
1"
#130000
0"
#135000
b1 *
b10100001 &
b10100001 (
b10100001 +
b1 )
1"
#140000
0"
#145000
b10 *
1$
1"
#150000
0"
#155000
b10 -
1,
b10100001 %
b10100001 .
1/
1"
#160000
0"
#165000
1'
b1 -
1"
#170000
0"
#175000
b0 -
b11 *
1"
#180000
0"
#185000
b100 *
0$
1"
#190000
0"
#195000
0,
0/
1"
#200000
0"
#205000
0'
1"
#210000
0"
#215000
b101 *
1"
#220000
0"
#225000
b1 *
b10100010 &
b10100010 (
b10100010 +
b10 )
1"
#230000
0"
#235000
b10 *
1$
1"
#240000
0"
#245000
b10 -
1,
b10100010 %
b10100010 .
1/
1"
#250000
0"
#255000
1'
b1 -
1"
#260000
0"
#265000
b11 *
b0 -
1"
#270000
0"
#275000
b100 *
0$
1"
#280000
0"
#285000
0,
0/
1"
#290000
0"
#295000
0'
1"
#300000
0"
#305000
b101 *
1"
#310000
0"
#315000
b1 *
b10100011 &
b10100011 (
b10100011 +
b11 )
1"
#320000
0"
#325000
b10 *
1$
1"
#330000
0"
#335000
b10 -
1,
b10100011 %
b10100011 .
1/
1"
#340000
0"
#345000
1'
b1 -
1"
#350000
0"
#355000
b0 -
b11 *
1"
#360000
0"
#365000
b100 *
0$
1"
#370000
0"
#375000
0,
0/
1"
#380000
0"
#385000
0'
1"
#390000
0"
#395000
b110 *
1"
#400000
0"
#405000
b0 *
1!
1"
#410000
0"
#415000
b1 *
b10100000 &
b10100000 (
b10100000 +
b0 )
0!
1"
#420000
0"
#425000
b10 *
1$
1"
